{
    "登记员":"好大",
    "来电号码":"123213",
    "时间":"16:45:41",
    "咨询内容":"投诉与建议",
    "日期":"2017-10-31"
}{
    "登记员":"好大割",
    "来电号码":"342",
    "时间":"16:46:01",
    "咨询内容":"设备维修",
    "日期":"2017-10-31"
}{
    "登记员":"",
    "日期":"2017-10-31",
    "来电号码":"",
    "咨询内容":"设备维修",
    "时间":"16:58:45"
}{
    "时间":"16:59:05",
    "日期":"2017-10-31",
    "咨询内容":"投诉与建议",
    "登记员":"234",
    "来电号码":"234"
}{
    "时间":"16:59:27",
    "来电号码":"234",
    "咨询内容":"新网点申办咨询",
    "登记员":"234",
    "日期":"2017-10-31"
}{
    "日期":"2017-10-31",
    "时间":"17:00:55",
    "来电号码":"234",
    "登记员":"234",
    "咨询内容":"投诉与建议"
}{
    "日期":"2017-10-31",
    "登记员":"234",
    "来电号码":"23",
    "时间":"17:02:06",
    "咨询内容":"投诉与建议"
}{
    "登记员":"234",
    "日期":"2017-10-31",
    "咨询内容":"设备维修",
    "时间":"17:05:16",
    "来电号码":"234"
}{
    "时间":"17:06:03",
    "登记员":"234",
    "来电号码":"234",
    "日期":"2017-10-31",
    "咨询内容":"请选择"
}{
    "日期":"2017-10-31",
    "时间":"17:07:51",
    "咨询内容":"设备维修",
    "来电号码":"234",
    "登记员":"234"
}{
    "时间":"17:08:08",
    "登记员":"234",
    "咨询内容":"开奖号码查询",
    "日期":"2017-10-31",
    "来电号码":"234"
}{
    "时间":"17:11:09",
    "登记员":"234",
    "日期":"2017-10-31",
    "咨询内容":"设备维修",
    "来电号码":"234"
}